{
  "id": "173308d5-8fdf-47a9-a141-f4998eb0f39a",
  "prevId": "bd65c894-4fc7-4707-a0cc-47ec2d546513",
  "version": "7",
  "dialect": "postgresql",
  "tables": {
    "public.account": {
      "name": "account",
      "schema": "",
      "columns": {
        "id": {
          "name": "id",
          "type": "text",
          "primaryKey": true,
          "notNull": true
        },
        "accountId": {
          "name": "accountId",
          "type": "text",
          "primaryKey": false,
          "notNull": true
        },
        "providerId": {
          "name": "providerId",
          "type": "text",
          "primaryKey": false,
          "notNull": true
        },
        "userId": {
          "name": "userId",
          "type": "text",
          "primaryKey": false,
          "notNull": true
        },
        "accessToken": {
          "name": "accessToken",
          "type": "text",
          "primaryKey": false,
          "notNull": false
        },
        "refreshToken": {
          "name": "refreshToken",
          "type": "text",
          "primaryKey": false,
          "notNull": false
        },
        "idToken": {
          "name": "idToken",
          "type": "text",
          "primaryKey": false,
          "notNull": false
        },
        "expiresAt": {
          "name": "expiresAt",
          "type": "timestamp",
          "primaryKey": false,
          "notNull": false
        },
        "password": {
          "name": "password",
          "type": "text",
          "primaryKey": false,
          "notNull": false
        }
      },
      "indexes": {},
      "foreignKeys": {
        "account_userId_user_id_fk": {
          "name": "account_userId_user_id_fk",
          "tableFrom": "account",
          "tableTo": "user",
          "columnsFrom": [
            "userId"
          ],
          "columnsTo": [
            "id"
          ],
          "onDelete": "no action",
          "onUpdate": "no action"
        }
      },
      "compositePrimaryKeys": {},
      "uniqueConstraints": {}
    },
    "public.session": {
      "name": "session",
      "schema": "",
      "columns": {
        "id": {
          "name": "id",
          "type": "text",
          "primaryKey": true,
          "notNull": true
        },
        "expiresAt": {
          "name": "expiresAt",
          "type": "timestamp",
          "primaryKey": false,
          "notNull": true
        },
        "ipAddress": {
          "name": "ipAddress",
          "type": "text",
          "primaryKey": false,
          "notNull": false
        },
        "userAgent": {
          "name": "userAgent",
          "type": "text",
          "primaryKey": false,
          "notNull": false
        },
        "userId": {
          "name": "userId",
          "type": "text",
          "primaryKey": false,
          "notNull": true
        }
      },
      "indexes": {},
      "foreignKeys": {
        "session_userId_user_id_fk": {
          "name": "session_userId_user_id_fk",
          "tableFrom": "session",
          "tableTo": "user",
          "columnsFrom": [
            "userId"
          ],
          "columnsTo": [
            "id"
          ],
          "onDelete": "no action",
          "onUpdate": "no action"
        }
      },
      "compositePrimaryKeys": {},
      "uniqueConstraints": {}
    },
    "public.user": {
      "name": "user",
      "schema": "",
      "columns": {
        "id": {
          "name": "id",
          "type": "text",
          "primaryKey": true,
          "notNull": true
        },
        "name": {
          "name": "name",
          "type": "text",
          "primaryKey": false,
          "notNull": true
        },
        "email": {
          "name": "email",
          "type": "text",
          "primaryKey": false,
          "notNull": true
        },
        "emailVerified": {
          "name": "emailVerified",
          "type": "boolean",
          "primaryKey": false,
          "notNull": true
        },
        "image": {
          "name": "image",
          "type": "text",
          "primaryKey": false,
          "notNull": false
        },
        "createdAt": {
          "name": "createdAt",
          "type": "timestamp",
          "primaryKey": false,
          "notNull": true
        },
        "updatedAt": {
          "name": "updatedAt",
          "type": "timestamp",
          "primaryKey": false,
          "notNull": true
        }
      },
      "indexes": {},
      "foreignKeys": {},
      "compositePrimaryKeys": {},
      "uniqueConstraints": {
        "user_email_unique": {
          "name": "user_email_unique",
          "nullsNotDistinct": false,
          "columns": [
            "email"
          ]
        }
      }
    },
    "public.verification": {
      "name": "verification",
      "schema": "",
      "columns": {
        "id": {
          "name": "id",
          "type": "text",
          "primaryKey": true,
          "notNull": true
        },
        "identifier": {
          "name": "identifier",
          "type": "text",
          "primaryKey": false,
          "notNull": true
        },
        "value": {
          "name": "value",
          "type": "text",
          "primaryKey": false,
          "notNull": true
        },
        "expiresAt": {
          "name": "expiresAt",
          "type": "timestamp",
          "primaryKey": false,
          "notNull": true
        }
      },
      "indexes": {},
      "foreignKeys": {},
      "compositePrimaryKeys": {},
      "uniqueConstraints": {}
    },
    "public.product_category": {
      "name": "product_category",
      "schema": "",
      "columns": {
        "id": {
          "name": "id",
          "type": "serial",
          "primaryKey": true,
          "notNull": true
        },
        "name": {
          "name": "name",
          "type": "text",
          "primaryKey": false,
          "notNull": true
        },
        "status": {
          "name": "status",
          "type": "boolean",
          "primaryKey": false,
          "notNull": true,
          "default": true
        }
      },
      "indexes": {},
      "foreignKeys": {},
      "compositePrimaryKeys": {},
      "uniqueConstraints": {}
    },
    "public.product": {
      "name": "product",
      "schema": "",
      "columns": {
        "id": {
          "name": "id",
          "type": "serial",
          "primaryKey": true,
          "notNull": true
        },
        "sku": {
          "name": "sku",
          "type": "text",
          "primaryKey": false,
          "notNull": true
        },
        "name": {
          "name": "name",
          "type": "text",
          "primaryKey": false,
          "notNull": true
        },
        "description": {
          "name": "description",
          "type": "text",
          "primaryKey": false,
          "notNull": true
        },
        "category_id": {
          "name": "category_id",
          "type": "integer",
          "primaryKey": false,
          "notNull": true
        },
        "price": {
          "name": "price",
          "type": "integer",
          "primaryKey": false,
          "notNull": true
        },
        "user_id": {
          "name": "user_id",
          "type": "text",
          "primaryKey": false,
          "notNull": true
        }
      },
      "indexes": {},
      "foreignKeys": {
        "product_category_id_product_category_id_fk": {
          "name": "product_category_id_product_category_id_fk",
          "tableFrom": "product",
          "tableTo": "product_category",
          "columnsFrom": [
            "category_id"
          ],
          "columnsTo": [
            "id"
          ],
          "onDelete": "cascade",
          "onUpdate": "no action"
        },
        "product_user_id_user_id_fk": {
          "name": "product_user_id_user_id_fk",
          "tableFrom": "product",
          "tableTo": "user",
          "columnsFrom": [
            "user_id"
          ],
          "columnsTo": [
            "id"
          ],
          "onDelete": "no action",
          "onUpdate": "no action"
        }
      },
      "compositePrimaryKeys": {},
      "uniqueConstraints": {}
    },
    "public.supplier": {
      "name": "supplier",
      "schema": "",
      "columns": {
        "id": {
          "name": "id",
          "type": "serial",
          "primaryKey": true,
          "notNull": true
        },
        "name": {
          "name": "name",
          "type": "text",
          "primaryKey": false,
          "notNull": true
        },
        "address": {
          "name": "address",
          "type": "text",
          "primaryKey": false,
          "notNull": true
        },
        "phone": {
          "name": "phone",
          "type": "text",
          "primaryKey": false,
          "notNull": false
        },
        "email": {
          "name": "email",
          "type": "text",
          "primaryKey": false,
          "notNull": false
        }
      },
      "indexes": {},
      "foreignKeys": {},
      "compositePrimaryKeys": {},
      "uniqueConstraints": {}
    },
    "public.customer": {
      "name": "customer",
      "schema": "",
      "columns": {
        "id": {
          "name": "id",
          "type": "serial",
          "primaryKey": true,
          "notNull": true
        },
        "name": {
          "name": "name",
          "type": "text",
          "primaryKey": false,
          "notNull": true
        },
        "position": {
          "name": "position",
          "type": "text",
          "primaryKey": false,
          "notNull": true
        }
      },
      "indexes": {},
      "foreignKeys": {},
      "compositePrimaryKeys": {},
      "uniqueConstraints": {}
    },
    "public.purchase_order_cart_item": {
      "name": "purchase_order_cart_item",
      "schema": "",
      "columns": {
        "id": {
          "name": "id",
          "type": "serial",
          "primaryKey": true,
          "notNull": true
        },
        "cart_id": {
          "name": "cart_id",
          "type": "integer",
          "primaryKey": false,
          "notNull": false
        },
        "product_id": {
          "name": "product_id",
          "type": "integer",
          "primaryKey": false,
          "notNull": true
        },
        "quantity": {
          "name": "quantity",
          "type": "integer",
          "primaryKey": false,
          "notNull": true
        }
      },
      "indexes": {},
      "foreignKeys": {
        "purchase_order_cart_item_cart_id_purchase_order_cart_id_fk": {
          "name": "purchase_order_cart_item_cart_id_purchase_order_cart_id_fk",
          "tableFrom": "purchase_order_cart_item",
          "tableTo": "purchase_order_cart",
          "columnsFrom": [
            "cart_id"
          ],
          "columnsTo": [
            "id"
          ],
          "onDelete": "cascade",
          "onUpdate": "no action"
        },
        "purchase_order_cart_item_product_id_product_id_fk": {
          "name": "purchase_order_cart_item_product_id_product_id_fk",
          "tableFrom": "purchase_order_cart_item",
          "tableTo": "product",
          "columnsFrom": [
            "product_id"
          ],
          "columnsTo": [
            "id"
          ],
          "onDelete": "cascade",
          "onUpdate": "no action"
        }
      },
      "compositePrimaryKeys": {},
      "uniqueConstraints": {}
    },
    "public.purchase_order_cart": {
      "name": "purchase_order_cart",
      "schema": "",
      "columns": {
        "id": {
          "name": "id",
          "type": "serial",
          "primaryKey": true,
          "notNull": true
        },
        "supplier_id": {
          "name": "supplier_id",
          "type": "integer",
          "primaryKey": false,
          "notNull": true
        },
        "created_at": {
          "name": "created_at",
          "type": "timestamp",
          "primaryKey": false,
          "notNull": true,
          "default": "now()"
        },
        "updated_at": {
          "name": "updated_at",
          "type": "timestamp",
          "primaryKey": false,
          "notNull": true,
          "default": "now()"
        }
      },
      "indexes": {},
      "foreignKeys": {
        "purchase_order_cart_supplier_id_supplier_id_fk": {
          "name": "purchase_order_cart_supplier_id_supplier_id_fk",
          "tableFrom": "purchase_order_cart",
          "tableTo": "supplier",
          "columnsFrom": [
            "supplier_id"
          ],
          "columnsTo": [
            "id"
          ],
          "onDelete": "no action",
          "onUpdate": "no action"
        }
      },
      "compositePrimaryKeys": {},
      "uniqueConstraints": {}
    },
    "public.purchase_order_item": {
      "name": "purchase_order_item",
      "schema": "",
      "columns": {
        "id": {
          "name": "id",
          "type": "serial",
          "primaryKey": true,
          "notNull": true
        },
        "purchase_order_id": {
          "name": "purchase_order_id",
          "type": "integer",
          "primaryKey": false,
          "notNull": true
        },
        "product_id": {
          "name": "product_id",
          "type": "integer",
          "primaryKey": false,
          "notNull": true
        },
        "quantity": {
          "name": "quantity",
          "type": "integer",
          "primaryKey": false,
          "notNull": true
        }
      },
      "indexes": {},
      "foreignKeys": {
        "purchase_order_item_purchase_order_id_purchase_order_id_fk": {
          "name": "purchase_order_item_purchase_order_id_purchase_order_id_fk",
          "tableFrom": "purchase_order_item",
          "tableTo": "purchase_order",
          "columnsFrom": [
            "purchase_order_id"
          ],
          "columnsTo": [
            "id"
          ],
          "onDelete": "cascade",
          "onUpdate": "no action"
        },
        "purchase_order_item_product_id_product_id_fk": {
          "name": "purchase_order_item_product_id_product_id_fk",
          "tableFrom": "purchase_order_item",
          "tableTo": "product",
          "columnsFrom": [
            "product_id"
          ],
          "columnsTo": [
            "id"
          ],
          "onDelete": "no action",
          "onUpdate": "no action"
        }
      },
      "compositePrimaryKeys": {},
      "uniqueConstraints": {}
    },
    "public.purchase_order": {
      "name": "purchase_order",
      "schema": "",
      "columns": {
        "id": {
          "name": "id",
          "type": "serial",
          "primaryKey": true,
          "notNull": true
        },
        "supplier_id": {
          "name": "supplier_id",
          "type": "integer",
          "primaryKey": false,
          "notNull": true
        },
        "order_date": {
          "name": "order_date",
          "type": "timestamp",
          "primaryKey": false,
          "notNull": true,
          "default": "now()"
        },
        "po_code": {
          "name": "po_code",
          "type": "varchar(20)",
          "primaryKey": false,
          "notNull": true
        },
        "status": {
          "name": "status",
          "type": "purchase_order_status",
          "typeSchema": "public",
          "primaryKey": false,
          "notNull": true,
          "default": "'pending'"
        }
      },
      "indexes": {},
      "foreignKeys": {
        "purchase_order_supplier_id_supplier_id_fk": {
          "name": "purchase_order_supplier_id_supplier_id_fk",
          "tableFrom": "purchase_order",
          "tableTo": "supplier",
          "columnsFrom": [
            "supplier_id"
          ],
          "columnsTo": [
            "id"
          ],
          "onDelete": "no action",
          "onUpdate": "no action"
        }
      },
      "compositePrimaryKeys": {},
      "uniqueConstraints": {}
    },
    "public.sales_order_cart_item": {
      "name": "sales_order_cart_item",
      "schema": "",
      "columns": {
        "id": {
          "name": "id",
          "type": "serial",
          "primaryKey": true,
          "notNull": true
        },
        "cart_id": {
          "name": "cart_id",
          "type": "integer",
          "primaryKey": false,
          "notNull": true
        },
        "product_id": {
          "name": "product_id",
          "type": "integer",
          "primaryKey": false,
          "notNull": true
        },
        "quantity": {
          "name": "quantity",
          "type": "integer",
          "primaryKey": false,
          "notNull": true
        },
        "selling_price": {
          "name": "selling_price",
          "type": "integer",
          "primaryKey": false,
          "notNull": true
        }
      },
      "indexes": {},
      "foreignKeys": {
        "sales_order_cart_item_cart_id_sales_order_cart_id_fk": {
          "name": "sales_order_cart_item_cart_id_sales_order_cart_id_fk",
          "tableFrom": "sales_order_cart_item",
          "tableTo": "sales_order_cart",
          "columnsFrom": [
            "cart_id"
          ],
          "columnsTo": [
            "id"
          ],
          "onDelete": "cascade",
          "onUpdate": "no action"
        },
        "sales_order_cart_item_product_id_product_id_fk": {
          "name": "sales_order_cart_item_product_id_product_id_fk",
          "tableFrom": "sales_order_cart_item",
          "tableTo": "product",
          "columnsFrom": [
            "product_id"
          ],
          "columnsTo": [
            "id"
          ],
          "onDelete": "cascade",
          "onUpdate": "no action"
        }
      },
      "compositePrimaryKeys": {},
      "uniqueConstraints": {}
    },
    "public.sales_order_cart": {
      "name": "sales_order_cart",
      "schema": "",
      "columns": {
        "id": {
          "name": "id",
          "type": "serial",
          "primaryKey": true,
          "notNull": true
        },
        "customer_id": {
          "name": "customer_id",
          "type": "integer",
          "primaryKey": false,
          "notNull": true
        },
        "created_at": {
          "name": "created_at",
          "type": "timestamp",
          "primaryKey": false,
          "notNull": true,
          "default": "now()"
        },
        "updated_at": {
          "name": "updated_at",
          "type": "timestamp",
          "primaryKey": false,
          "notNull": true,
          "default": "now()"
        }
      },
      "indexes": {},
      "foreignKeys": {
        "sales_order_cart_customer_id_customer_id_fk": {
          "name": "sales_order_cart_customer_id_customer_id_fk",
          "tableFrom": "sales_order_cart",
          "tableTo": "customer",
          "columnsFrom": [
            "customer_id"
          ],
          "columnsTo": [
            "id"
          ],
          "onDelete": "no action",
          "onUpdate": "no action"
        }
      },
      "compositePrimaryKeys": {},
      "uniqueConstraints": {}
    },
    "public.inventory_items": {
      "name": "inventory_items",
      "schema": "",
      "columns": {
        "id": {
          "name": "id",
          "type": "serial",
          "primaryKey": true,
          "notNull": true
        },
        "product_id": {
          "name": "product_id",
          "type": "integer",
          "primaryKey": false,
          "notNull": true
        },
        "stock_in": {
          "name": "stock_in",
          "type": "integer",
          "primaryKey": false,
          "notNull": false,
          "default": 0
        },
        "stock_out": {
          "name": "stock_out",
          "type": "integer",
          "primaryKey": false,
          "notNull": false,
          "default": 0
        }
      },
      "indexes": {},
      "foreignKeys": {
        "inventory_items_product_id_product_id_fk": {
          "name": "inventory_items_product_id_product_id_fk",
          "tableFrom": "inventory_items",
          "tableTo": "product",
          "columnsFrom": [
            "product_id"
          ],
          "columnsTo": [
            "id"
          ],
          "onDelete": "cascade",
          "onUpdate": "no action"
        }
      },
      "compositePrimaryKeys": {},
      "uniqueConstraints": {}
    }
  },
  "enums": {
    "public.purchase_order_status": {
      "name": "purchase_order_status",
      "schema": "public",
      "values": [
        "pending",
        "approved",
        "rejected",
        "completed"
      ]
    },
    "public.sales_order_status": {
      "name": "sales_order_status",
      "schema": "public",
      "values": [
        "pending",
        "approved",
        "rejected",
        "completed"
      ]
    }
  },
  "schemas": {},
  "sequences": {},
  "_meta": {
    "columns": {},
    "schemas": {},
    "tables": {}
  }
}